<?xml version="1.0" encoding="utf-8"?><Transactions><Transaction ID="" Terminal="1241" ChnNum="4060001"><TranNum>14885</TranNum><JournalNum>406</JournalNum><TranAmount>4</TranAmount><TranDiscount>0</TranDiscount><TranCashDiscount>0</TranCashDiscount><tChange>0</tChange><TranDate>2013-06-03</TranDate><TranTime>08:49:59</TranTime><IsRefund>0</IsRefund><IsDebtPayment>1</IsDebtPayment><CashierFlag>1</CashierFlag><CashierNum>1</CashierNum><AmountDiscountType>0</AmountDiscountType><ClubDealFlag>0</ClubDealFlag><CustID>0</CustID><AmountDiscountPercent>0</AmountDiscountPercent><RefundMode>0</RefundMode><Components><Component ID=""><PluCode>1</PluCode><Title>כללי</Title><CompAmount>4</CompAmount><CompCashDiscount>0</CompCashDiscount><CompDiscount>0</CompDiscount><CodeFlag>1</CodeFlag><StockAmount>1</StockAmount><DiscountType>0</DiscountType><SecondDiscFlag>0</SecondDiscFlag><SecondFreeFlag>0</SecondFreeFlag><OtherDiscountFlag>0</OtherDiscountFlag><ClubDiscount>0</ClubDiscount><AmountPercentDiscount>0</AmountPercentDiscount><DepartmentFlag>0</DepartmentFlag><DepartmentNum>0</DepartmentNum><WeigthFlag>0</WeigthFlag><WeightQty>1</WeightQty></Component></Components><Payments><Payment ID=""><PaymID>1</PaymID><CashSum>4</CashSum><ChequeSum>0.00</ChequeSum><FullData>0</FullData><ChequeNumber></ChequeNumber><PayDate></PayDate><BankNo>0</BankNo><BankDeptNo>0</BankDeptNo><BankCntNo></BankCntNo><CouponSum>0.00</CouponSum><CouponNumber>0</CouponNumber><FrnCurrSum>0.00</FrnCurrSum><CurrencyID>0</CurrencyID><IsInShekels>0</IsInShekels><CreditCardSum>0.00</CreditCardSum><FirstPayment>0.00</FirstPayment><OtherPayment>0.00</OtherPayment><CardNum></CardNum><ExpDate>0</ExpDate><CreditTerms>0</CreditTerms><CompanyNum>0</CompanyNum><NumPayments>0</NumPayments><TranCode>0</TranCode><TranType>0</TranType><AuthorizCode>0</AuthorizCode><Currency>0</Currency><AuthorizNo>0</AuthorizNo><Deposited>0</Deposited><Track2></Track2><Track2Len>0</Track2Len><FileNum>0</FileNum><CTransCount>0</CTransCount><ComReason>0</ComReason><CochavAmount>0.00</CochavAmount><ClubCode>0</ClubCode><HakafaSum>0.00</HakafaSum><CustID>0</CustID><IsRefundVoucher>0</IsRefundVoucher><IsChangingVoucher>0</IsChangingVoucher></Payment></Payments></Transaction><Transaction ID="" Terminal="1241" ChnNum="4060002"><TranNum>14886</TranNum><JournalNum>406</JournalNum><TranAmount>63</TranAmount><TranDiscount>0</TranDiscount><TranCashDiscount>0</TranCashDiscount><tChange>0</tChange><TranDate>2013-06-03</TranDate><TranTime>10:33:09</TranTime><IsRefund>0</IsRefund><IsDebtPayment>1</IsDebtPayment><CashierFlag>1</CashierFlag><CashierNum>1</CashierNum><AmountDiscountType>0</AmountDiscountType><ClubDealFlag>0</ClubDealFlag><CustID>0</CustID><AmountDiscountPercent>0</AmountDiscountPercent><RefundMode>0</RefundMode><Components><Component ID=""><PluCode>12297</PluCode><Title>דבק סופר גלו 13 גרם</Title><CompAmount>15</CompAmount><CompCashDiscount>0</CompCashDiscount><CompDiscount>0</CompDiscount><CodeFlag>1</CodeFlag><StockAmount>1</StockAmount><DiscountType>0</DiscountType><SecondDiscFlag>0</SecondDiscFlag><SecondFreeFlag>0</SecondFreeFlag><OtherDiscountFlag>0</OtherDiscountFlag><ClubDiscount>0</ClubDiscount><AmountPercentDiscount>0</AmountPercentDiscount><DepartmentFlag>0</DepartmentFlag><DepartmentNum>0</DepartmentNum><WeigthFlag>0</WeigthFlag><WeightQty>1</WeightQty></Component><Component ID=""><PluCode>1</PluCode><Title>ספריי ניקל</Title><CompAmount>24</CompAmount><CompCashDiscount>0</CompCashDiscount><CompDiscount>0</CompDiscount><CodeFlag>1</CodeFlag><StockAmount>2</StockAmount><DiscountType>0</DiscountType><SecondDiscFlag>0</SecondDiscFlag><SecondFreeFlag>0</SecondFreeFlag><OtherDiscountFlag>0</OtherDiscountFlag><ClubDiscount>0</ClubDiscount><AmountPercentDiscount>0</AmountPercentDiscount><DepartmentFlag>0</DepartmentFlag><DepartmentNum>0</DepartmentNum><WeigthFlag>0</WeigthFlag><WeightQty>2</WeightQty></Component></Components><Payments><Payment ID=""><PaymID>1</PaymID><CashSum>63</CashSum><ChequeSum>0.00</ChequeSum><FullData>0</FullData><ChequeNumber></ChequeNumber><PayDate></PayDate><BankNo>0</BankNo><BankDeptNo>0</BankDeptNo><BankCntNo></BankCntNo><CouponSum>0.00</CouponSum><CouponNumber>0</CouponNumber><FrnCurrSum>0.00</FrnCurrSum><CurrencyID>0</CurrencyID><IsInShekels>0</IsInShekels><CreditCardSum>0.00</CreditCardSum><FirstPayment>0.00</FirstPayment><OtherPayment>0.00</OtherPayment><CardNum></CardNum><ExpDate>0</ExpDate><CreditTerms>0</CreditTerms><CompanyNum>0</CompanyNum><NumPayments>0</NumPayments><TranCode>0</TranCode><TranType>0</TranType><AuthorizCode>0</AuthorizCode><Currency>0</Currency><AuthorizNo>0</AuthorizNo><Deposited>0</Deposited><Track2></Track2><Track2Len>0</Track2Len><FileNum>0</FileNum><CTransCount>0</CTransCount><ComReason>0</ComReason><CochavAmount>0.00</CochavAmount><ClubCode>0</ClubCode><HakafaSum>0.00</HakafaSum><CustID>0</CustID><IsRefundVoucher>0</IsRefundVoucher><IsChangingVoucher>0</IsChangingVoucher></Payment></Payments></Transaction><Transaction ID="" Terminal="1241" ChnNum="4060003"><TranNum>14887</TranNum><JournalNum>406</JournalNum><TranAmount>4</TranAmount><TranDiscount>0</TranDiscount><TranCashDiscount>0</TranCashDiscount><tChange>0</tChange><TranDate>2013-06-03</TranDate><TranTime>10:35:04</TranTime><IsRefund>0</IsRefund><IsDebtPayment>1</IsDebtPayment><CashierFlag>1</CashierFlag><CashierNum>1</CashierNum><AmountDiscountType>0</AmountDiscountType><ClubDealFlag>0</ClubDealFlag><CustID>0</CustID><AmountDiscountPercent>0</AmountDiscountPercent><RefundMode>0</RefundMode><Components><Component ID=""><PluCode>1</PluCode><Title>כללי</Title><CompAmount>4</CompAmount><CompCashDiscount>0</CompCashDiscount><CompDiscount>0</CompDiscount><CodeFlag>1</CodeFlag><StockAmount>1</StockAmount><DiscountType>0</DiscountType><SecondDiscFlag>0</SecondDiscFlag><SecondFreeFlag>0</SecondFreeFlag><OtherDiscountFlag>0</OtherDiscountFlag><ClubDiscount>0</ClubDiscount><AmountPercentDiscount>0</AmountPercentDiscount><DepartmentFlag>0</DepartmentFlag><DepartmentNum>0</DepartmentNum><WeigthFlag>0</WeigthFlag><WeightQty>1</WeightQty></Component></Components><Payments><Payment ID=""><PaymID>1</PaymID><CashSum>4</CashSum><ChequeSum>0.00</ChequeSum><FullData>0</FullData><ChequeNumber></ChequeNumber><PayDate></PayDate><BankNo>0</BankNo><BankDeptNo>0</BankDeptNo><BankCntNo></BankCntNo><CouponSum>0.00</CouponSum><CouponNumber>0</CouponNumber><FrnCurrSum>0.00</FrnCurrSum><CurrencyID>0</CurrencyID><IsInShekels>0</IsInShekels><CreditCardSum>0.00</CreditCardSum><FirstPayment>0.00</FirstPayment><OtherPayment>0.00</OtherPayment><CardNum></CardNum><ExpDate>0</ExpDate><CreditTerms>0</CreditTerms><CompanyNum>0</CompanyNum><NumPayments>0</NumPayments><TranCode>0</TranCode><TranType>0</TranType><AuthorizCode>0</AuthorizCode><Currency>0</Currency><AuthorizNo>0</AuthorizNo><Deposited>0</Deposited><Track2></Track2><Track2Len>0</Track2Len><FileNum>0</FileNum><CTransCount>0</CTransCount><ComReason>0</ComReason><CochavAmount>0.00</CochavAmount><ClubCode>0</ClubCode><HakafaSum>0.00</HakafaSum><CustID>0</CustID><IsRefundVoucher>0</IsRefundVoucher><IsChangingVoucher>0</IsChangingVoucher></Payment></Payments></Transaction><Transaction ID="" Terminal="1241" ChnNum="4060004"><TranNum>14888</TranNum><JournalNum>406</JournalNum><TranAmount>50</TranAmount><TranDiscount>0</TranDiscount><TranCashDiscount>0</TranCashDiscount><tChange>0</tChange><TranDate>2013-06-03</TranDate><TranTime>11:13:30</TranTime><IsRefund>0</IsRefund><IsDebtPayment>1</IsDebtPayment><CashierFlag>1</CashierFlag><CashierNum>1</CashierNum><AmountDiscountType>0</AmountDiscountType><ClubDealFlag>0</ClubDealFlag><CustID>0</CustID><AmountDiscountPercent>0</AmountDiscountPercent><RefundMode>0</RefundMode><Components><Component ID=""><PluCode>1</PluCode><Title>כללי</Title><CompAmount>50</CompAmount><CompCashDiscount>0</CompCashDiscount><CompDiscount>0</CompDiscount><CodeFlag>1</CodeFlag><StockAmount>1</StockAmount><DiscountType>0</DiscountType><SecondDiscFlag>0</SecondDiscFlag><SecondFreeFlag>0</SecondFreeFlag><OtherDiscountFlag>0</OtherDiscountFlag><ClubDiscount>0</ClubDiscount><AmountPercentDiscount>0</AmountPercentDiscount><DepartmentFlag>0</DepartmentFlag><DepartmentNum>0</DepartmentNum><WeigthFlag>0</WeigthFlag><WeightQty>1</WeightQty></Component></Components><Payments><Payment ID=""><PaymID>1</PaymID><CashSum>50</CashSum><ChequeSum>0.00</ChequeSum><FullData>0</FullData><ChequeNumber></ChequeNumber><PayDate></PayDate><BankNo>0</BankNo><BankDeptNo>0</BankDeptNo><BankCntNo></BankCntNo><CouponSum>0.00</CouponSum><CouponNumber>0</CouponNumber><FrnCurrSum>0.00</FrnCurrSum><CurrencyID>0</CurrencyID><IsInShekels>0</IsInShekels><CreditCardSum>0.00</CreditCardSum><FirstPayment>0.00</FirstPayment><OtherPayment>0.00</OtherPayment><CardNum></CardNum><ExpDate>0</ExpDate><CreditTerms>0</CreditTerms><CompanyNum>0</CompanyNum><NumPayments>0</NumPayments><TranCode>0</TranCode><TranType>0</TranType><AuthorizCode>0</AuthorizCode><Currency>0</Currency><AuthorizNo>0</AuthorizNo><Deposited>0</Deposited><Track2></Track2><Track2Len>0</Track2Len><FileNum>0</FileNum><CTransCount>0</CTransCount><ComReason>0</ComReason><CochavAmount>0.00</CochavAmount><ClubCode>0</ClubCode><HakafaSum>0.00</HakafaSum><CustID>0</CustID><IsRefundVoucher>0</IsRefundVoucher><IsChangingVoucher>0</IsChangingVoucher></Payment></Payments></Transaction><Transaction ID="" Terminal="1241" ChnNum="4060005"><TranNum>14889</TranNum><JournalNum>406</JournalNum><TranAmount>4</TranAmount><TranDiscount>0</TranDiscount><TranCashDiscount>0</TranCashDiscount><tChange>0</tChange><TranDate>2013-06-03</TranDate><TranTime>11:51:11</TranTime><IsRefund>0</IsRefund><IsDebtPayment>1</IsDebtPayment><CashierFlag>1</CashierFlag><CashierNum>1</CashierNum><AmountDiscountType>0</AmountDiscountType><ClubDealFlag>0</ClubDealFlag><CustID>0</CustID><AmountDiscountPercent>0</AmountDiscountPercent><RefundMode>0</RefundMode><Components><Component ID=""><PluCode>1</PluCode><Title>כללי</Title><CompAmount>4</CompAmount><CompCashDiscount>0</CompCashDiscount><CompDiscount>0</CompDiscount><CodeFlag>1</CodeFlag><StockAmount>1</StockAmount><DiscountType>0</DiscountType><SecondDiscFlag>0</SecondDiscFlag><SecondFreeFlag>0</SecondFreeFlag><OtherDiscountFlag>0</OtherDiscountFlag><ClubDiscount>0</ClubDiscount><AmountPercentDiscount>0</AmountPercentDiscount><DepartmentFlag>0</DepartmentFlag><DepartmentNum>0</DepartmentNum><WeigthFlag>0</WeigthFlag><WeightQty>1</WeightQty></Component></Components><Payments><Payment ID=""><PaymID>1</PaymID><CashSum>4</CashSum><ChequeSum>0.00</ChequeSum><FullData>0</FullData><ChequeNumber></ChequeNumber><PayDate></PayDate><BankNo>0</BankNo><BankDeptNo>0</BankDeptNo><BankCntNo></BankCntNo><CouponSum>0.00</CouponSum><CouponNumber>0</CouponNumber><FrnCurrSum>0.00</FrnCurrSum><CurrencyID>0</CurrencyID><IsInShekels>0</IsInShekels><CreditCardSum>0.00</CreditCardSum><FirstPayment>0.00</FirstPayment><OtherPayment>0.00</OtherPayment><CardNum></CardNum><ExpDate>0</ExpDate><CreditTerms>0</CreditTerms><CompanyNum>0</CompanyNum><NumPayments>0</NumPayments><TranCode>0</TranCode><TranType>0</TranType><AuthorizCode>0</AuthorizCode><Currency>0</Currency><AuthorizNo>0</AuthorizNo><Deposited>0</Deposited><Track2></Track2><Track2Len>0</Track2Len><FileNum>0</FileNum><CTransCount>0</CTransCount><ComReason>0</ComReason><CochavAmount>0.00</CochavAmount><ClubCode>0</ClubCode><HakafaSum>0.00</HakafaSum><CustID>0</CustID><IsRefundVoucher>0</IsRefundVoucher><IsChangingVoucher>0</IsChangingVoucher></Payment></Payments></Transaction><Transaction ID="" Terminal="1241" ChnNum="4060006"><TranNum>14890</TranNum><JournalNum>406</JournalNum><TranAmount>4.5</TranAmount><TranDiscount>0</TranDiscount><TranCashDiscount>0</TranCashDiscount><tChange>0</tChange><TranDate>2013-06-03</TranDate><TranTime>11:51:25</TranTime><IsRefund>0</IsRefund><IsDebtPayment>1</IsDebtPayment><CashierFlag>1</CashierFlag><CashierNum>1</CashierNum><AmountDiscountType>0</AmountDiscountType><ClubDealFlag>0</ClubDealFlag><CustID>0</CustID><AmountDiscountPercent>0</AmountDiscountPercent><RefundMode>0</RefundMode><Components><Component ID=""><PluCode>1</PluCode><Title>כללי</Title><CompAmount>4.5</CompAmount><CompCashDiscount>0</CompCashDiscount><CompDiscount>0</CompDiscount><CodeFlag>1</CodeFlag><StockAmount>1</StockAmount><DiscountType>0</DiscountType><SecondDiscFlag>0</SecondDiscFlag><SecondFreeFlag>0</SecondFreeFlag><OtherDiscountFlag>0</OtherDiscountFlag><ClubDiscount>0</ClubDiscount><AmountPercentDiscount>0</AmountPercentDiscount><DepartmentFlag>0</DepartmentFlag><DepartmentNum>0</DepartmentNum><WeigthFlag>0</WeigthFlag><WeightQty>1</WeightQty></Component></Components><Payments><Payment ID=""><PaymID>1</PaymID><CashSum>4.5</CashSum><ChequeSum>0.00</ChequeSum><FullData>0</FullData><ChequeNumber></ChequeNumber><PayDate></PayDate><BankNo>0</BankNo><BankDeptNo>0</BankDeptNo><BankCntNo></BankCntNo><CouponSum>0.00</CouponSum><CouponNumber>0</CouponNumber><FrnCurrSum>0.00</FrnCurrSum><CurrencyID>0</CurrencyID><IsInShekels>0</IsInShekels><CreditCardSum>0.00</CreditCardSum><FirstPayment>0.00</FirstPayment><OtherPayment>0.00</OtherPayment><CardNum></CardNum><ExpDate>0</ExpDate><CreditTerms>0</CreditTerms><CompanyNum>0</CompanyNum><NumPayments>0</NumPayments><TranCode>0</TranCode><TranType>0</TranType><AuthorizCode>0</AuthorizCode><Currency>0</Currency><AuthorizNo>0</AuthorizNo><Deposited>0</Deposited><Track2></Track2><Track2Len>0</Track2Len><FileNum>0</FileNum><CTransCount>0</CTransCount><ComReason>0</ComReason><CochavAmount>0.00</CochavAmount><ClubCode>0</ClubCode><HakafaSum>0.00</HakafaSum><CustID>0</CustID><IsRefundVoucher>0</IsRefundVoucher><IsChangingVoucher>0</IsChangingVoucher></Payment></Payments></Transaction><Transaction ID="" Terminal="1241" ChnNum="4060007"><TranNum>14891</TranNum><JournalNum>406</JournalNum><TranAmount>62.9</TranAmount><TranDiscount>0</TranDiscount><TranCashDiscount>0</TranCashDiscount><tChange>0</tChange><TranDate>2013-06-03</TranDate><TranTime>11:57:34</TranTime><IsRefund>0</IsRefund><IsDebtPayment>1</IsDebtPayment><CashierFlag>1</CashierFlag><CashierNum>1</CashierNum><AmountDiscountType>0</AmountDiscountType><ClubDealFlag>0</ClubDealFlag><CustID>0</CustID><AmountDiscountPercent>0</AmountDiscountPercent><RefundMode>0</RefundMode><Components><Component ID=""><PluCode>1</PluCode><Title>כללי</Title><CompAmount>23</CompAmount><CompCashDiscount>0</CompCashDiscount><CompDiscount>0</CompDiscount><CodeFlag>1</CodeFlag><StockAmount>1</StockAmount><DiscountType>0</DiscountType><SecondDiscFlag>0</SecondDiscFlag><SecondFreeFlag>0</SecondFreeFlag><OtherDiscountFlag>0</OtherDiscountFlag><ClubDiscount>0</ClubDiscount><AmountPercentDiscount>0</AmountPercentDiscount><DepartmentFlag>0</DepartmentFlag><DepartmentNum>0</DepartmentNum><WeigthFlag>0</WeigthFlag><WeightQty>1</WeightQty></Component><Component ID=""><PluCode>7290008813044</PluCode><Title>וילון בד לאמבטיה 180X180</Title><CompAmount>39.9</CompAmount><CompCashDiscount>0</CompCashDiscount><CompDiscount>0</CompDiscount><CodeFlag>1</CodeFlag><StockAmount>1</StockAmount><DiscountType>0</DiscountType><SecondDiscFlag>0</SecondDiscFlag><SecondFreeFlag>0</SecondFreeFlag><OtherDiscountFlag>0</OtherDiscountFlag><ClubDiscount>0</ClubDiscount><AmountPercentDiscount>0</AmountPercentDiscount><DepartmentFlag>0</DepartmentFlag><DepartmentNum>0</DepartmentNum><WeigthFlag>0</WeigthFlag><WeightQty>1</WeightQty></Component></Components><Payments><Payment ID=""><PaymID>1</PaymID><CashSum>62.9</CashSum><ChequeSum>0.00</ChequeSum><FullData>0</FullData><ChequeNumber></ChequeNumber><PayDate></PayDate><BankNo>0</BankNo><BankDeptNo>0</BankDeptNo><BankCntNo></BankCntNo><CouponSum>0.00</CouponSum><CouponNumber>0</CouponNumber><FrnCurrSum>0.00</FrnCurrSum><CurrencyID>0</CurrencyID><IsInShekels>0</IsInShekels><CreditCardSum>0.00</CreditCardSum><FirstPayment>0.00</FirstPayment><OtherPayment>0.00</OtherPayment><CardNum></CardNum><ExpDate>0</ExpDate><CreditTerms>0</CreditTerms><CompanyNum>0</CompanyNum><NumPayments>0</NumPayments><TranCode>0</TranCode><TranType>0</TranType><AuthorizCode>0</AuthorizCode><Currency>0</Currency><AuthorizNo>0</AuthorizNo><Deposited>0</Deposited><Track2></Track2><Track2Len>0</Track2Len><FileNum>0</FileNum><CTransCount>0</CTransCount><ComReason>0</ComReason><CochavAmount>0.00</CochavAmount><ClubCode>0</ClubCode><HakafaSum>0.00</HakafaSum><CustID>0</CustID><IsRefundVoucher>0</IsRefundVoucher><IsChangingVoucher>0</IsChangingVoucher></Payment></Payments></Transaction><Transaction ID="" Terminal="1241" ChnNum="4060008"><TranNum>14892</TranNum><JournalNum>406</JournalNum><TranAmount>20</TranAmount><TranDiscount>0</TranDiscount><TranCashDiscount>0</TranCashDiscount><tChange>0</tChange><TranDate>2013-06-03</TranDate><TranTime>12:10:35</TranTime><IsRefund>0</IsRefund><IsDebtPayment>1</IsDebtPayment><CashierFlag>1</CashierFlag><CashierNum>1</CashierNum><AmountDiscountType>0</AmountDiscountType><ClubDealFlag>0</ClubDealFlag><CustID>0</CustID><AmountDiscountPercent>0</AmountDiscountPercent><RefundMode>0</RefundMode><Components><Component ID=""><PluCode>1</PluCode><Title>כללי</Title><CompAmount>20</CompAmount><CompCashDiscount>0</CompCashDiscount><CompDiscount>0</CompDiscount><CodeFlag>1</CodeFlag><StockAmount>1</StockAmount><DiscountType>0</DiscountType><SecondDiscFlag>0</SecondDiscFlag><SecondFreeFlag>0</SecondFreeFlag><OtherDiscountFlag>0</OtherDiscountFlag><ClubDiscount>0</ClubDiscount><AmountPercentDiscount>0</AmountPercentDiscount><DepartmentFlag>0</DepartmentFlag><DepartmentNum>0</DepartmentNum><WeigthFlag>0</WeigthFlag><WeightQty>1</WeightQty></Component></Components><Payments><Payment ID=""><PaymID>1</PaymID><CashSum>20</CashSum><ChequeSum>0.00</ChequeSum><FullData>0</FullData><ChequeNumber></ChequeNumber><PayDate></PayDate><BankNo>0</BankNo><BankDeptNo>0</BankDeptNo><BankCntNo></BankCntNo><CouponSum>0.00</CouponSum><CouponNumber>0</CouponNumber><FrnCurrSum>0.00</FrnCurrSum><CurrencyID>0</CurrencyID><IsInShekels>0</IsInShekels><CreditCardSum>0.00</CreditCardSum><FirstPayment>0.00</FirstPayment><OtherPayment>0.00</OtherPayment><CardNum></CardNum><ExpDate>0</ExpDate><CreditTerms>0</CreditTerms><CompanyNum>0</CompanyNum><NumPayments>0</NumPayments><TranCode>0</TranCode><TranType>0</TranType><AuthorizCode>0</AuthorizCode><Currency>0</Currency><AuthorizNo>0</AuthorizNo><Deposited>0</Deposited><Track2></Track2><Track2Len>0</Track2Len><FileNum>0</FileNum><CTransCount>0</CTransCount><ComReason>0</ComReason><CochavAmount>0.00</CochavAmount><ClubCode>0</ClubCode><HakafaSum>0.00</HakafaSum><CustID>0</CustID><IsRefundVoucher>0</IsRefundVoucher><IsChangingVoucher>0</IsChangingVoucher></Payment></Payments></Transaction><Transaction ID="" Terminal="1241" ChnNum="4060009"><TranNum>14893</TranNum><JournalNum>406</JournalNum><TranAmount>5</TranAmount><TranDiscount>0</TranDiscount><TranCashDiscount>0</TranCashDiscount><tChange>0</tChange><TranDate>2013-06-03</TranDate><TranTime>12:19:21</TranTime><IsRefund>0</IsRefund><IsDebtPayment>1</IsDebtPayment><CashierFlag>1</CashierFlag><CashierNum>1</CashierNum><AmountDiscountType>0</AmountDiscountType><ClubDealFlag>0</ClubDealFlag><CustID>0</CustID><AmountDiscountPercent>0</AmountDiscountPercent><RefundMode>0</RefundMode><Components><Component ID=""><PluCode>1</PluCode><Title>כללי</Title><CompAmount>5</CompAmount><CompCashDiscount>0</CompCashDiscount><CompDiscount>0</CompDiscount><CodeFlag>1</CodeFlag><StockAmount>1</StockAmount><DiscountType>0</DiscountType><SecondDiscFlag>0</SecondDiscFlag><SecondFreeFlag>0</SecondFreeFlag><OtherDiscountFlag>0</OtherDiscountFlag><ClubDiscount>0</ClubDiscount><AmountPercentDiscount>0</AmountPercentDiscount><DepartmentFlag>0</DepartmentFlag><DepartmentNum>0</DepartmentNum><WeigthFlag>0</WeigthFlag><WeightQty>1</WeightQty></Component></Components><Payments><Payment ID=""><PaymID>1</PaymID><CashSum>5</CashSum><ChequeSum>0.00</ChequeSum><FullData>0</FullData><ChequeNumber></ChequeNumber><PayDate></PayDate><BankNo>0</BankNo><BankDeptNo>0</BankDeptNo><BankCntNo></BankCntNo><CouponSum>0.00</CouponSum><CouponNumber>0</CouponNumber><FrnCurrSum>0.00</FrnCurrSum><CurrencyID>0</CurrencyID><IsInShekels>0</IsInShekels><CreditCardSum>0.00</CreditCardSum><FirstPayment>0.00</FirstPayment><OtherPayment>0.00</OtherPayment><CardNum></CardNum><ExpDate>0</ExpDate><CreditTerms>0</CreditTerms><CompanyNum>0</CompanyNum><NumPayments>0</NumPayments><TranCode>0</TranCode><TranType>0</TranType><AuthorizCode>0</AuthorizCode><Currency>0</Currency><AuthorizNo>0</AuthorizNo><Deposited>0</Deposited><Track2></Track2><Track2Len>0</Track2Len><FileNum>0</FileNum><CTransCount>0</CTransCount><ComReason>0</ComReason><CochavAmount>0.00</CochavAmount><ClubCode>0</ClubCode><HakafaSum>0.00</HakafaSum><CustID>0</CustID><IsRefundVoucher>0</IsRefundVoucher><IsChangingVoucher>0</IsChangingVoucher></Payment></Payments></Transaction><Transaction ID="" Terminal="1241" ChnNum="4060010"><TranNum>14894</TranNum><JournalNum>406</JournalNum><TranAmount>67</TranAmount><TranDiscount>0</TranDiscount><TranCashDiscount>0</TranCashDiscount><tChange>0</tChange><TranDate>2013-06-03</TranDate><TranTime>13:08:55</TranTime><IsRefund>0</IsRefund><IsDebtPayment>1</IsDebtPayment><CashierFlag>1</CashierFlag><CashierNum>1</CashierNum><AmountDiscountType>0</AmountDiscountType><ClubDealFlag>0</ClubDealFlag><CustID>0</CustID><AmountDiscountPercent>0</AmountDiscountPercent><RefundMode>0</RefundMode><Components><Component ID=""><PluCode>1</PluCode><Title>כללי</Title><CompAmount>67</CompAmount><CompCashDiscount>0</CompCashDiscount><CompDiscount>0</CompDiscount><CodeFlag>1</CodeFlag><StockAmount>1</StockAmount><DiscountType>0</DiscountType><SecondDiscFlag>0</SecondDiscFlag><SecondFreeFlag>0</SecondFreeFlag><OtherDiscountFlag>0</OtherDiscountFlag><ClubDiscount>0</ClubDiscount><AmountPercentDiscount>0</AmountPercentDiscount><DepartmentFlag>0</DepartmentFlag><DepartmentNum>0</DepartmentNum><WeigthFlag>0</WeigthFlag><WeightQty>1</WeightQty></Component></Components><Payments><Payment ID=""><PaymID>1</PaymID><CashSum>67</CashSum><ChequeSum>0.00</ChequeSum><FullData>0</FullData><ChequeNumber></ChequeNumber><PayDate></PayDate><BankNo>0</BankNo><BankDeptNo>0</BankDeptNo><BankCntNo></BankCntNo><CouponSum>0.00</CouponSum><CouponNumber>0</CouponNumber><FrnCurrSum>0.00</FrnCurrSum><CurrencyID>0</CurrencyID><IsInShekels>0</IsInShekels><CreditCardSum>0.00</CreditCardSum><FirstPayment>0.00</FirstPayment><OtherPayment>0.00</OtherPayment><CardNum></CardNum><ExpDate>0</ExpDate><CreditTerms>0</CreditTerms><CompanyNum>0</CompanyNum><NumPayments>0</NumPayments><TranCode>0</TranCode><TranType>0</TranType><AuthorizCode>0</AuthorizCode><Currency>0</Currency><AuthorizNo>0</AuthorizNo><Deposited>0</Deposited><Track2></Track2><Track2Len>0</Track2Len><FileNum>0</FileNum><CTransCount>0</CTransCount><ComReason>0</ComReason><CochavAmount>0.00</CochavAmount><ClubCode>0</ClubCode><HakafaSum>0.00</HakafaSum><CustID>0</CustID><IsRefundVoucher>0</IsRefundVoucher><IsChangingVoucher>0</IsChangingVoucher></Payment></Payments></Transaction><Transaction ID="" Terminal="1241" ChnNum="4060011"><TranNum>14895</TranNum><JournalNum>406</JournalNum><TranAmount>33</TranAmount><TranDiscount>0</TranDiscount><TranCashDiscount>0</TranCashDiscount><tChange>0</tChange><TranDate>2013-06-03</TranDate><TranTime>13:24:53</TranTime><IsRefund>0</IsRefund><IsDebtPayment>1</IsDebtPayment><CashierFlag>1</CashierFlag><CashierNum>1</CashierNum><AmountDiscountType>0</AmountDiscountType><ClubDealFlag>0</ClubDealFlag><CustID>0</CustID><AmountDiscountPercent>0</AmountDiscountPercent><RefundMode>0</RefundMode><Components><Component ID=""><PluCode>38711</PluCode><Title>סט  רולר פאר+מגש+ספוג 10 ס"מ</Title><CompAmount>18</CompAmount><CompCashDiscount>0</CompCashDiscount><CompDiscount>0</CompDiscount><CodeFlag>1</CodeFlag><StockAmount>1</StockAmount><DiscountType>0</DiscountType><SecondDiscFlag>0</SecondDiscFlag><SecondFreeFlag>0</SecondFreeFlag><OtherDiscountFlag>0</OtherDiscountFlag><ClubDiscount>0</ClubDiscount><AmountPercentDiscount>0</AmountPercentDiscount><DepartmentFlag>0</DepartmentFlag><DepartmentNum>0</DepartmentNum><WeigthFlag>0</WeigthFlag><WeightQty>1</WeightQty></Component><Component ID=""><PluCode>1</PluCode><Title>כללי</Title><CompAmount>15</CompAmount><CompCashDiscount>0</CompCashDiscount><CompDiscount>0</CompDiscount><CodeFlag>1</CodeFlag><StockAmount>1</StockAmount><DiscountType>0</DiscountType><SecondDiscFlag>0</SecondDiscFlag><SecondFreeFlag>0</SecondFreeFlag><OtherDiscountFlag>0</OtherDiscountFlag><ClubDiscount>0</ClubDiscount><AmountPercentDiscount>0</AmountPercentDiscount><DepartmentFlag>0</DepartmentFlag><DepartmentNum>0</DepartmentNum><WeigthFlag>0</WeigthFlag><WeightQty>1</WeightQty></Component></Components><Payments><Payment ID=""><PaymID>1</PaymID><CashSum>33</CashSum><ChequeSum>0.00</ChequeSum><FullData>0</FullData><ChequeNumber></ChequeNumber><PayDate></PayDate><BankNo>0</BankNo><BankDeptNo>0</BankDeptNo><BankCntNo></BankCntNo><CouponSum>0.00</CouponSum><CouponNumber>0</CouponNumber><FrnCurrSum>0.00</FrnCurrSum><CurrencyID>0</CurrencyID><IsInShekels>0</IsInShekels><CreditCardSum>0.00</CreditCardSum><FirstPayment>0.00</FirstPayment><OtherPayment>0.00</OtherPayment><CardNum></CardNum><ExpDate>0</ExpDate><CreditTerms>0</CreditTerms><CompanyNum>0</CompanyNum><NumPayments>0</NumPayments><TranCode>0</TranCode><TranType>0</TranType><AuthorizCode>0</AuthorizCode><Currency>0</Currency><AuthorizNo>0</AuthorizNo><Deposited>0</Deposited><Track2></Track2><Track2Len>0</Track2Len><FileNum>0</FileNum><CTransCount>0</CTransCount><ComReason>0</ComReason><CochavAmount>0.00</CochavAmount><ClubCode>0</ClubCode><HakafaSum>0.00</HakafaSum><CustID>0</CustID><IsRefundVoucher>0</IsRefundVoucher><IsChangingVoucher>0</IsChangingVoucher></Payment></Payments></Transaction><Transaction ID="" Terminal="1241" ChnNum="4060012"><TranNum>14896</TranNum><JournalNum>406</JournalNum><TranAmount>15</TranAmount><TranDiscount>0</TranDiscount><TranCashDiscount>0</TranCashDiscount><tChange>0</tChange><TranDate>2013-06-03</TranDate><TranTime>13:47:44</TranTime><IsRefund>0</IsRefund><IsDebtPayment>1</IsDebtPayment><CashierFlag>1</CashierFlag><CashierNum>1</CashierNum><AmountDiscountType>0</AmountDiscountType><ClubDealFlag>0</ClubDealFlag><CustID>0</CustID><AmountDiscountPercent>0</AmountDiscountPercent><RefundMode>0</RefundMode><Components><Component ID=""><PluCode>1</PluCode><Title>כללי</Title><CompAmount>15</CompAmount><CompCashDiscount>0</CompCashDiscount><CompDiscount>0</CompDiscount><CodeFlag>1</CodeFlag><StockAmount>1</StockAmount><DiscountType>0</DiscountType><SecondDiscFlag>0</SecondDiscFlag><SecondFreeFlag>0</SecondFreeFlag><OtherDiscountFlag>0</OtherDiscountFlag><ClubDiscount>0</ClubDiscount><AmountPercentDiscount>0</AmountPercentDiscount><DepartmentFlag>0</DepartmentFlag><DepartmentNum>0</DepartmentNum><WeigthFlag>0</WeigthFlag><WeightQty>1</WeightQty></Component></Components><Payments><Payment ID=""><PaymID>1</PaymID><CashSum>15</CashSum><ChequeSum>0.00</ChequeSum><FullData>0</FullData><ChequeNumber></ChequeNumber><PayDate></PayDate><BankNo>0</BankNo><BankDeptNo>0</BankDeptNo><BankCntNo></BankCntNo><CouponSum>0.00</CouponSum><CouponNumber>0</CouponNumber><FrnCurrSum>0.00</FrnCurrSum><CurrencyID>0</CurrencyID><IsInShekels>0</IsInShekels><CreditCardSum>0.00</CreditCardSum><FirstPayment>0.00</FirstPayment><OtherPayment>0.00</OtherPayment><CardNum></CardNum><ExpDate>0</ExpDate><CreditTerms>0</CreditTerms><CompanyNum>0</CompanyNum><NumPayments>0</NumPayments><TranCode>0</TranCode><TranType>0</TranType><AuthorizCode>0</AuthorizCode><Currency>0</Currency><AuthorizNo>0</AuthorizNo><Deposited>0</Deposited><Track2></Track2><Track2Len>0</Track2Len><FileNum>0</FileNum><CTransCount>0</CTransCount><ComReason>0</ComReason><CochavAmount>0.00</CochavAmount><ClubCode>0</ClubCode><HakafaSum>0.00</HakafaSum><CustID>0</CustID><IsRefundVoucher>0</IsRefundVoucher><IsChangingVoucher>0</IsChangingVoucher></Payment></Payments></Transaction><Transaction ID="" Terminal="1241" ChnNum="4060013"><TranNum>14897</TranNum><JournalNum>406</JournalNum><TranAmount>168</TranAmount><TranDiscount>0</TranDiscount><TranCashDiscount>0</TranCashDiscount><tChange>0</tChange><TranDate>2013-06-03</TranDate><TranTime>14:49:31</TranTime><IsRefund>0</IsRefund><IsDebtPayment>1</IsDebtPayment><CashierFlag>1</CashierFlag><CashierNum>1</CashierNum><AmountDiscountType>0</AmountDiscountType><ClubDealFlag>0</ClubDealFlag><CustID>0</CustID><AmountDiscountPercent>0</AmountDiscountPercent><RefundMode>0</RefundMode><Components><Component ID=""><PluCode>100154</PluCode><Title>פרופשיונאל סכין מיני 15 ס"מ ARCOSTEEL</Title><CompAmount>100</CompAmount><CompCashDiscount>0</CompCashDiscount><CompDiscount>0</CompDiscount><CodeFlag>1</CodeFlag><StockAmount>1</StockAmount><DiscountType>0</DiscountType><SecondDiscFlag>0</SecondDiscFlag><SecondFreeFlag>0</SecondFreeFlag><OtherDiscountFlag>0</OtherDiscountFlag><ClubDiscount>0</ClubDiscount><AmountPercentDiscount>0</AmountPercentDiscount><DepartmentFlag>0</DepartmentFlag><DepartmentNum>0</DepartmentNum><WeigthFlag>0</WeigthFlag><WeightQty>1</WeightQty></Component><Component ID=""><PluCode>100638</PluCode><Title>אקסל סכין סנטוקו 18 ס"מ ARCOSTEEL</Title><CompAmount>60</CompAmount><CompCashDiscount>0</CompCashDiscount><CompDiscount>0</CompDiscount><CodeFlag>1</CodeFlag><StockAmount>1</StockAmount><DiscountType>0</DiscountType><SecondDiscFlag>0</SecondDiscFlag><SecondFreeFlag>0</SecondFreeFlag><OtherDiscountFlag>0</OtherDiscountFlag><ClubDiscount>0</ClubDiscount><AmountPercentDiscount>0</AmountPercentDiscount><DepartmentFlag>0</DepartmentFlag><DepartmentNum>0</DepartmentNum><WeigthFlag>0</WeigthFlag><WeightQty>1</WeightQty></Component><Component ID=""><PluCode>1</PluCode><Title>כללי</Title><CompAmount>2</CompAmount><CompCashDiscount>0</CompCashDiscount><CompDiscount>0</CompDiscount><CodeFlag>1</CodeFlag><StockAmount>4</StockAmount><DiscountType>0</DiscountType><SecondDiscFlag>0</SecondDiscFlag><SecondFreeFlag>0</SecondFreeFlag><OtherDiscountFlag>0</OtherDiscountFlag><ClubDiscount>0</ClubDiscount><AmountPercentDiscount>0</AmountPercentDiscount><DepartmentFlag>0</DepartmentFlag><DepartmentNum>0</DepartmentNum><WeigthFlag>0</WeigthFlag><WeightQty>4</WeightQty></Component></Components><Payments><Payment ID=""><PaymID>5</PaymID><CashSum>0.00</CashSum><ChequeSum>0.00</ChequeSum><FullData>0</FullData><ChequeNumber></ChequeNumber><PayDate></PayDate><BankNo>0</BankNo><BankDeptNo>0</BankDeptNo><BankCntNo></BankCntNo><CouponSum>0.00</CouponSum><CouponNumber>0</CouponNumber><FrnCurrSum>0.00</FrnCurrSum><CurrencyID>0</CurrencyID><IsInShekels>0</IsInShekels><CreditCardSum>168</CreditCardSum><FirstPayment>168</FirstPayment><OtherPayment>168</OtherPayment><CardNum>375512191196600</CardNum><ExpDate>2015-11-01 00:00:00</ExpDate><CreditTerms>1</CreditTerms><CompanyNum>4</CompanyNum><NumPayments>1</NumPayments><TranCode>Regular</TranCode><TranType>1</TranType><AuthorizCode>Manual</AuthorizCode><Currency>1</Currency><AuthorizNo></AuthorizNo><Deposited>0</Deposited><Track2></Track2><Track2Len>0</Track2Len><FileNum>0</FileNum><CTransCount>0</CTransCount><ComReason>2</ComReason><CochavAmount>0</CochavAmount><ClubCode>0</ClubCode><HakafaSum>0.00</HakafaSum><CustID>0</CustID><IsRefundVoucher>0</IsRefundVoucher><IsChangingVoucher>0</IsChangingVoucher></Payment></Payments></Transaction><Transaction ID="" Terminal="1241" ChnNum="4060014"><TranNum>14898</TranNum><JournalNum>406</JournalNum><TranAmount>1</TranAmount><TranDiscount>0</TranDiscount><TranCashDiscount>0</TranCashDiscount><tChange>0</tChange><TranDate>2013-06-03</TranDate><TranTime>15:21:50</TranTime><IsRefund>0</IsRefund><IsDebtPayment>1</IsDebtPayment><CashierFlag>1</CashierFlag><CashierNum>1</CashierNum><AmountDiscountType>0</AmountDiscountType><ClubDealFlag>0</ClubDealFlag><CustID>0</CustID><AmountDiscountPercent>0</AmountDiscountPercent><RefundMode>0</RefundMode><Components><Component ID=""><PluCode>1</PluCode><Title>כללי</Title><CompAmount>1</CompAmount><CompCashDiscount>0</CompCashDiscount><CompDiscount>0</CompDiscount><CodeFlag>1</CodeFlag><StockAmount>1</StockAmount><DiscountType>0</DiscountType><SecondDiscFlag>0</SecondDiscFlag><SecondFreeFlag>0</SecondFreeFlag><OtherDiscountFlag>0</OtherDiscountFlag><ClubDiscount>0</ClubDiscount><AmountPercentDiscount>0</AmountPercentDiscount><DepartmentFlag>0</DepartmentFlag><DepartmentNum>0</DepartmentNum><WeigthFlag>0</WeigthFlag><WeightQty>1</WeightQty></Component></Components><Payments><Payment ID=""><PaymID>1</PaymID><CashSum>1</CashSum><ChequeSum>0.00</ChequeSum><FullData>0</FullData><ChequeNumber></ChequeNumber><PayDate></PayDate><BankNo>0</BankNo><BankDeptNo>0</BankDeptNo><BankCntNo></BankCntNo><CouponSum>0.00</CouponSum><CouponNumber>0</CouponNumber><FrnCurrSum>0.00</FrnCurrSum><CurrencyID>0</CurrencyID><IsInShekels>0</IsInShekels><CreditCardSum>0.00</CreditCardSum><FirstPayment>0.00</FirstPayment><OtherPayment>0.00</OtherPayment><CardNum></CardNum><ExpDate>0</ExpDate><CreditTerms>0</CreditTerms><CompanyNum>0</CompanyNum><NumPayments>0</NumPayments><TranCode>0</TranCode><TranType>0</TranType><AuthorizCode>0</AuthorizCode><Currency>0</Currency><AuthorizNo>0</AuthorizNo><Deposited>0</Deposited><Track2></Track2><Track2Len>0</Track2Len><FileNum>0</FileNum><CTransCount>0</CTransCount><ComReason>0</ComReason><CochavAmount>0.00</CochavAmount><ClubCode>0</ClubCode><HakafaSum>0.00</HakafaSum><CustID>0</CustID><IsRefundVoucher>0</IsRefundVoucher><IsChangingVoucher>0</IsChangingVoucher></Payment></Payments></Transaction><Transaction ID="" Terminal="1241" ChnNum="4060015"><TranNum>14899</TranNum><JournalNum>406</JournalNum><TranAmount>54</TranAmount><TranDiscount>0</TranDiscount><TranCashDiscount>0</TranCashDiscount><tChange>0</tChange><TranDate>2013-06-03</TranDate><TranTime>15:41:50</TranTime><IsRefund>0</IsRefund><IsDebtPayment>1</IsDebtPayment><CashierFlag>1</CashierFlag><CashierNum>1</CashierNum><AmountDiscountType>0</AmountDiscountType><ClubDealFlag>0</ClubDealFlag><CustID>0</CustID><AmountDiscountPercent>0</AmountDiscountPercent><RefundMode>0</RefundMode><Components><Component ID=""><PluCode>87821</PluCode><Title>מברשת "בומבה" שיער "3 טבעי פאר</Title><CompAmount>39</CompAmount><CompCashDiscount>0</CompCashDiscount><CompDiscount>0</CompDiscount><CodeFlag>1</CodeFlag><StockAmount>1</StockAmount><DiscountType>0</DiscountType><SecondDiscFlag>0</SecondDiscFlag><SecondFreeFlag>0</SecondFreeFlag><OtherDiscountFlag>0</OtherDiscountFlag><ClubDiscount>0</ClubDiscount><AmountPercentDiscount>0</AmountPercentDiscount><DepartmentFlag>0</DepartmentFlag><DepartmentNum>0</DepartmentNum><WeigthFlag>0</WeigthFlag><WeightQty>1</WeightQty></Component><Component ID=""><PluCode>12658</PluCode><Title>אקדח סיליקון כתום</Title><CompAmount>15</CompAmount><CompCashDiscount>0</CompCashDiscount><CompDiscount>0</CompDiscount><CodeFlag>1</CodeFlag><StockAmount>1</StockAmount><DiscountType>0</DiscountType><SecondDiscFlag>0</SecondDiscFlag><SecondFreeFlag>0</SecondFreeFlag><OtherDiscountFlag>0</OtherDiscountFlag><ClubDiscount>0</ClubDiscount><AmountPercentDiscount>0</AmountPercentDiscount><DepartmentFlag>0</DepartmentFlag><DepartmentNum>0</DepartmentNum><WeigthFlag>0</WeigthFlag><WeightQty>1</WeightQty></Component></Components><Payments><Payment ID=""><PaymID>5</PaymID><CashSum>0.00</CashSum><ChequeSum>0.00</ChequeSum><FullData>0</FullData><ChequeNumber></ChequeNumber><PayDate></PayDate><BankNo>0</BankNo><BankDeptNo>0</BankDeptNo><BankCntNo></BankCntNo><CouponSum>0.00</CouponSum><CouponNumber>0</CouponNumber><FrnCurrSum>0.00</FrnCurrSum><CurrencyID>0</CurrencyID><IsInShekels>0</IsInShekels><CreditCardSum>54</CreditCardSum><FirstPayment>54</FirstPayment><OtherPayment>54</OtherPayment><CardNum>4580030293872955</CardNum><ExpDate>2015-09-01 00:00:00</ExpDate><CreditTerms>1</CreditTerms><CompanyNum>2</CompanyNum><NumPayments>1</NumPayments><TranCode>Regular</TranCode><TranType>1</TranType><AuthorizCode>Manual</AuthorizCode><Currency>1</Currency><AuthorizNo></AuthorizNo><Deposited>0</Deposited><Track2></Track2><Track2Len>0</Track2Len><FileNum>0</FileNum><CTransCount>0</CTransCount><ComReason>2</ComReason><CochavAmount>0</CochavAmount><ClubCode>0</ClubCode><HakafaSum>0.00</HakafaSum><CustID>0</CustID><IsRefundVoucher>0</IsRefundVoucher><IsChangingVoucher>0</IsChangingVoucher></Payment></Payments></Transaction><Transaction ID="" Terminal="1241" ChnNum="4060016"><TranNum>14900</TranNum><JournalNum>406</JournalNum><TranAmount>13</TranAmount><TranDiscount>0</TranDiscount><TranCashDiscount>0</TranCashDiscount><tChange>0</tChange><TranDate>2013-06-03</TranDate><TranTime>15:44:15</TranTime><IsRefund>0</IsRefund><IsDebtPayment>1</IsDebtPayment><CashierFlag>1</CashierFlag><CashierNum>1</CashierNum><AmountDiscountType>0</AmountDiscountType><ClubDealFlag>0</ClubDealFlag><CustID>0</CustID><AmountDiscountPercent>0</AmountDiscountPercent><RefundMode>0</RefundMode><Components><Component ID=""><PluCode>8447</PluCode><Title>חבק פלסטי 3.6X250</Title><CompAmount>13</CompAmount><CompCashDiscount>0</CompCashDiscount><CompDiscount>0</CompDiscount><CodeFlag>1</CodeFlag><StockAmount>1</StockAmount><DiscountType>0</DiscountType><SecondDiscFlag>0</SecondDiscFlag><SecondFreeFlag>0</SecondFreeFlag><OtherDiscountFlag>0</OtherDiscountFlag><ClubDiscount>0</ClubDiscount><AmountPercentDiscount>0</AmountPercentDiscount><DepartmentFlag>0</DepartmentFlag><DepartmentNum>0</DepartmentNum><WeigthFlag>0</WeigthFlag><WeightQty>1</WeightQty></Component></Components><Payments><Payment ID=""><PaymID>1</PaymID><CashSum>13</CashSum><ChequeSum>0.00</ChequeSum><FullData>0</FullData><ChequeNumber></ChequeNumber><PayDate></PayDate><BankNo>0</BankNo><BankDeptNo>0</BankDeptNo><BankCntNo></BankCntNo><CouponSum>0.00</CouponSum><CouponNumber>0</CouponNumber><FrnCurrSum>0.00</FrnCurrSum><CurrencyID>0</CurrencyID><IsInShekels>0</IsInShekels><CreditCardSum>0.00</CreditCardSum><FirstPayment>0.00</FirstPayment><OtherPayment>0.00</OtherPayment><CardNum></CardNum><ExpDate>0</ExpDate><CreditTerms>0</CreditTerms><CompanyNum>0</CompanyNum><NumPayments>0</NumPayments><TranCode>0</TranCode><TranType>0</TranType><AuthorizCode>0</AuthorizCode><Currency>0</Currency><AuthorizNo>0</AuthorizNo><Deposited>0</Deposited><Track2></Track2><Track2Len>0</Track2Len><FileNum>0</FileNum><CTransCount>0</CTransCount><ComReason>0</ComReason><CochavAmount>0.00</CochavAmount><ClubCode>0</ClubCode><HakafaSum>0.00</HakafaSum><CustID>0</CustID><IsRefundVoucher>0</IsRefundVoucher><IsChangingVoucher>0</IsChangingVoucher></Payment></Payments></Transaction><Transaction ID="" Terminal="1241" ChnNum="4060017"><TranNum>14901</TranNum><JournalNum>406</JournalNum><TranAmount>14</TranAmount><TranDiscount>0</TranDiscount><TranCashDiscount>0</TranCashDiscount><tChange>0</tChange><TranDate>2013-06-03</TranDate><TranTime>16:04:00</TranTime><IsRefund>0</IsRefund><IsDebtPayment>1</IsDebtPayment><CashierFlag>1</CashierFlag><CashierNum>1</CashierNum><AmountDiscountType>0</AmountDiscountType><ClubDealFlag>0</ClubDealFlag><CustID>0</CustID><AmountDiscountPercent>0</AmountDiscountPercent><RefundMode>0</RefundMode><Components><Component ID=""><PluCode>1</PluCode><Title>כללי</Title><CompAmount>14</CompAmount><CompCashDiscount>0</CompCashDiscount><CompDiscount>0</CompDiscount><CodeFlag>1</CodeFlag><StockAmount>1</StockAmount><DiscountType>0</DiscountType><SecondDiscFlag>0</SecondDiscFlag><SecondFreeFlag>0</SecondFreeFlag><OtherDiscountFlag>0</OtherDiscountFlag><ClubDiscount>0</ClubDiscount><AmountPercentDiscount>0</AmountPercentDiscount><DepartmentFlag>0</DepartmentFlag><DepartmentNum>0</DepartmentNum><WeigthFlag>0</WeigthFlag><WeightQty>1</WeightQty></Component></Components><Payments><Payment ID=""><PaymID>1</PaymID><CashSum>14</CashSum><ChequeSum>0.00</ChequeSum><FullData>0</FullData><ChequeNumber></ChequeNumber><PayDate></PayDate><BankNo>0</BankNo><BankDeptNo>0</BankDeptNo><BankCntNo></BankCntNo><CouponSum>0.00</CouponSum><CouponNumber>0</CouponNumber><FrnCurrSum>0.00</FrnCurrSum><CurrencyID>0</CurrencyID><IsInShekels>0</IsInShekels><CreditCardSum>0.00</CreditCardSum><FirstPayment>0.00</FirstPayment><OtherPayment>0.00</OtherPayment><CardNum></CardNum><ExpDate>0</ExpDate><CreditTerms>0</CreditTerms><CompanyNum>0</CompanyNum><NumPayments>0</NumPayments><TranCode>0</TranCode><TranType>0</TranType><AuthorizCode>0</AuthorizCode><Currency>0</Currency><AuthorizNo>0</AuthorizNo><Deposited>0</Deposited><Track2></Track2><Track2Len>0</Track2Len><FileNum>0</FileNum><CTransCount>0</CTransCount><ComReason>0</ComReason><CochavAmount>0.00</CochavAmount><ClubCode>0</ClubCode><HakafaSum>0.00</HakafaSum><CustID>0</CustID><IsRefundVoucher>0</IsRefundVoucher><IsChangingVoucher>0</IsChangingVoucher></Payment></Payments></Transaction><Transaction ID="" Terminal="1241" ChnNum="4060018"><TranNum>14902</TranNum><JournalNum>406</JournalNum><TranAmount>10</TranAmount><TranDiscount>0</TranDiscount><TranCashDiscount>0</TranCashDiscount><tChange>0</tChange><TranDate>2013-06-03</TranDate><TranTime>16:05:40</TranTime><IsRefund>0</IsRefund><IsDebtPayment>1</IsDebtPayment><CashierFlag>1</CashierFlag><CashierNum>1</CashierNum><AmountDiscountType>0</AmountDiscountType><ClubDealFlag>0</ClubDealFlag><CustID>0</CustID><AmountDiscountPercent>0</AmountDiscountPercent><RefundMode>0</RefundMode><Components><Component ID=""><PluCode>1</PluCode><Title>כללי</Title><CompAmount>10</CompAmount><CompCashDiscount>0</CompCashDiscount><CompDiscount>0</CompDiscount><CodeFlag>1</CodeFlag><StockAmount>1</StockAmount><DiscountType>0</DiscountType><SecondDiscFlag>0</SecondDiscFlag><SecondFreeFlag>0</SecondFreeFlag><OtherDiscountFlag>0</OtherDiscountFlag><ClubDiscount>0</ClubDiscount><AmountPercentDiscount>0</AmountPercentDiscount><DepartmentFlag>0</DepartmentFlag><DepartmentNum>0</DepartmentNum><WeigthFlag>0</WeigthFlag><WeightQty>1</WeightQty></Component></Components><Payments><Payment ID=""><PaymID>1</PaymID><CashSum>10</CashSum><ChequeSum>0.00</ChequeSum><FullData>0</FullData><ChequeNumber></ChequeNumber><PayDate></PayDate><BankNo>0</BankNo><BankDeptNo>0</BankDeptNo><BankCntNo></BankCntNo><CouponSum>0.00</CouponSum><CouponNumber>0</CouponNumber><FrnCurrSum>0.00</FrnCurrSum><CurrencyID>0</CurrencyID><IsInShekels>0</IsInShekels><CreditCardSum>0.00</CreditCardSum><FirstPayment>0.00</FirstPayment><OtherPayment>0.00</OtherPayment><CardNum></CardNum><ExpDate>0</ExpDate><CreditTerms>0</CreditTerms><CompanyNum>0</CompanyNum><NumPayments>0</NumPayments><TranCode>0</TranCode><TranType>0</TranType><AuthorizCode>0</AuthorizCode><Currency>0</Currency><AuthorizNo>0</AuthorizNo><Deposited>0</Deposited><Track2></Track2><Track2Len>0</Track2Len><FileNum>0</FileNum><CTransCount>0</CTransCount><ComReason>0</ComReason><CochavAmount>0.00</CochavAmount><ClubCode>0</ClubCode><HakafaSum>0.00</HakafaSum><CustID>0</CustID><IsRefundVoucher>0</IsRefundVoucher><IsChangingVoucher>0</IsChangingVoucher></Payment></Payments></Transaction><Transaction ID="" Terminal="1241" ChnNum="4060019"><TranNum>14903</TranNum><JournalNum>406</JournalNum><TranAmount>5</TranAmount><TranDiscount>0</TranDiscount><TranCashDiscount>0</TranCashDiscount><tChange>0</tChange><TranDate>2013-06-03</TranDate><TranTime>16:19:55</TranTime><IsRefund>0</IsRefund><IsDebtPayment>1</IsDebtPayment><CashierFlag>1</CashierFlag><CashierNum>1</CashierNum><AmountDiscountType>0</AmountDiscountType><ClubDealFlag>0</ClubDealFlag><CustID>0</CustID><AmountDiscountPercent>0</AmountDiscountPercent><RefundMode>0</RefundMode><Components><Component ID=""><PluCode>1</PluCode><Title>כללי</Title><CompAmount>5</CompAmount><CompCashDiscount>0</CompCashDiscount><CompDiscount>0</CompDiscount><CodeFlag>1</CodeFlag><StockAmount>1</StockAmount><DiscountType>0</DiscountType><SecondDiscFlag>0</SecondDiscFlag><SecondFreeFlag>0</SecondFreeFlag><OtherDiscountFlag>0</OtherDiscountFlag><ClubDiscount>0</ClubDiscount><AmountPercentDiscount>0</AmountPercentDiscount><DepartmentFlag>0</DepartmentFlag><DepartmentNum>0</DepartmentNum><WeigthFlag>0</WeigthFlag><WeightQty>1</WeightQty></Component></Components><Payments><Payment ID=""><PaymID>1</PaymID><CashSum>5</CashSum><ChequeSum>0.00</ChequeSum><FullData>0</FullData><ChequeNumber></ChequeNumber><PayDate></PayDate><BankNo>0</BankNo><BankDeptNo>0</BankDeptNo><BankCntNo></BankCntNo><CouponSum>0.00</CouponSum><CouponNumber>0</CouponNumber><FrnCurrSum>0.00</FrnCurrSum><CurrencyID>0</CurrencyID><IsInShekels>0</IsInShekels><CreditCardSum>0.00</CreditCardSum><FirstPayment>0.00</FirstPayment><OtherPayment>0.00</OtherPayment><CardNum></CardNum><ExpDate>0</ExpDate><CreditTerms>0</CreditTerms><CompanyNum>0</CompanyNum><NumPayments>0</NumPayments><TranCode>0</TranCode><TranType>0</TranType><AuthorizCode>0</AuthorizCode><Currency>0</Currency><AuthorizNo>0</AuthorizNo><Deposited>0</Deposited><Track2></Track2><Track2Len>0</Track2Len><FileNum>0</FileNum><CTransCount>0</CTransCount><ComReason>0</ComReason><CochavAmount>0.00</CochavAmount><ClubCode>0</ClubCode><HakafaSum>0.00</HakafaSum><CustID>0</CustID><IsRefundVoucher>0</IsRefundVoucher><IsChangingVoucher>0</IsChangingVoucher></Payment></Payments></Transaction><Transaction ID="" Terminal="1241" ChnNum="4060020"><TranNum>14904</TranNum><JournalNum>406</JournalNum><TranAmount>13</TranAmount><TranDiscount>0</TranDiscount><TranCashDiscount>0</TranCashDiscount><tChange>0</tChange><TranDate>2013-06-03</TranDate><TranTime>16:37:33</TranTime><IsRefund>0</IsRefund><IsDebtPayment>1</IsDebtPayment><CashierFlag>1</CashierFlag><CashierNum>1</CashierNum><AmountDiscountType>0</AmountDiscountType><ClubDealFlag>0</ClubDealFlag><CustID>0</CustID><AmountDiscountPercent>0</AmountDiscountPercent><RefundMode>0</RefundMode><Components><Component ID=""><PluCode>1</PluCode><Title>כללי</Title><CompAmount>13</CompAmount><CompCashDiscount>0</CompCashDiscount><CompDiscount>0</CompDiscount><CodeFlag>1</CodeFlag><StockAmount>1</StockAmount><DiscountType>0</DiscountType><SecondDiscFlag>0</SecondDiscFlag><SecondFreeFlag>0</SecondFreeFlag><OtherDiscountFlag>0</OtherDiscountFlag><ClubDiscount>0</ClubDiscount><AmountPercentDiscount>0</AmountPercentDiscount><DepartmentFlag>0</DepartmentFlag><DepartmentNum>0</DepartmentNum><WeigthFlag>0</WeigthFlag><WeightQty>1</WeightQty></Component></Components><Payments><Payment ID=""><PaymID>1</PaymID><CashSum>13</CashSum><ChequeSum>0.00</ChequeSum><FullData>0</FullData><ChequeNumber></ChequeNumber><PayDate></PayDate><BankNo>0</BankNo><BankDeptNo>0</BankDeptNo><BankCntNo></BankCntNo><CouponSum>0.00</CouponSum><CouponNumber>0</CouponNumber><FrnCurrSum>0.00</FrnCurrSum><CurrencyID>0</CurrencyID><IsInShekels>0</IsInShekels><CreditCardSum>0.00</CreditCardSum><FirstPayment>0.00</FirstPayment><OtherPayment>0.00</OtherPayment><CardNum></CardNum><ExpDate>0</ExpDate><CreditTerms>0</CreditTerms><CompanyNum>0</CompanyNum><NumPayments>0</NumPayments><TranCode>0</TranCode><TranType>0</TranType><AuthorizCode>0</AuthorizCode><Currency>0</Currency><AuthorizNo>0</AuthorizNo><Deposited>0</Deposited><Track2></Track2><Track2Len>0</Track2Len><FileNum>0</FileNum><CTransCount>0</CTransCount><ComReason>0</ComReason><CochavAmount>0.00</CochavAmount><ClubCode>0</ClubCode><HakafaSum>0.00</HakafaSum><CustID>0</CustID><IsRefundVoucher>0</IsRefundVoucher><IsChangingVoucher>0</IsChangingVoucher></Payment></Payments></Transaction><Transaction ID="" Terminal="1241" ChnNum="4060021"><TranNum>14905</TranNum><JournalNum>406</JournalNum><TranAmount>59</TranAmount><TranDiscount>0</TranDiscount><TranCashDiscount>0</TranCashDiscount><tChange>0</tChange><TranDate>2013-06-03</TranDate><TranTime>16:44:14</TranTime><IsRefund>0</IsRefund><IsDebtPayment>1</IsDebtPayment><CashierFlag>1</CashierFlag><CashierNum>1</CashierNum><AmountDiscountType>0</AmountDiscountType><ClubDealFlag>0</ClubDealFlag><CustID>0</CustID><AmountDiscountPercent>0</AmountDiscountPercent><RefundMode>0</RefundMode><Components><Component ID=""><PluCode>129526</PluCode><Title>סיפון "2 לכיור מטבח חוליות</Title><CompAmount>59</CompAmount><CompCashDiscount>0</CompCashDiscount><CompDiscount>0</CompDiscount><CodeFlag>1</CodeFlag><StockAmount>1</StockAmount><DiscountType>0</DiscountType><SecondDiscFlag>0</SecondDiscFlag><SecondFreeFlag>0</SecondFreeFlag><OtherDiscountFlag>0</OtherDiscountFlag><ClubDiscount>0</ClubDiscount><AmountPercentDiscount>0</AmountPercentDiscount><DepartmentFlag>0</DepartmentFlag><DepartmentNum>0</DepartmentNum><WeigthFlag>0</WeigthFlag><WeightQty>1</WeightQty></Component></Components><Payments><Payment ID=""><PaymID>1</PaymID><CashSum>59</CashSum><ChequeSum>0.00</ChequeSum><FullData>0</FullData><ChequeNumber></ChequeNumber><PayDate></PayDate><BankNo>0</BankNo><BankDeptNo>0</BankDeptNo><BankCntNo></BankCntNo><CouponSum>0.00</CouponSum><CouponNumber>0</CouponNumber><FrnCurrSum>0.00</FrnCurrSum><CurrencyID>0</CurrencyID><IsInShekels>0</IsInShekels><CreditCardSum>0.00</CreditCardSum><FirstPayment>0.00</FirstPayment><OtherPayment>0.00</OtherPayment><CardNum></CardNum><ExpDate>0</ExpDate><CreditTerms>0</CreditTerms><CompanyNum>0</CompanyNum><NumPayments>0</NumPayments><TranCode>0</TranCode><TranType>0</TranType><AuthorizCode>0</AuthorizCode><Currency>0</Currency><AuthorizNo>0</AuthorizNo><Deposited>0</Deposited><Track2></Track2><Track2Len>0</Track2Len><FileNum>0</FileNum><CTransCount>0</CTransCount><ComReason>0</ComReason><CochavAmount>0.00</CochavAmount><ClubCode>0</ClubCode><HakafaSum>0.00</HakafaSum><CustID>0</CustID><IsRefundVoucher>0</IsRefundVoucher><IsChangingVoucher>0</IsChangingVoucher></Payment></Payments></Transaction><Transaction ID="" Terminal="1241" ChnNum="4060022"><TranNum>14906</TranNum><JournalNum>406</JournalNum><TranAmount>8</TranAmount><TranDiscount>0</TranDiscount><TranCashDiscount>0</TranCashDiscount><tChange>0</tChange><TranDate>2013-06-03</TranDate><TranTime>16:50:28</TranTime><IsRefund>0</IsRefund><IsDebtPayment>1</IsDebtPayment><CashierFlag>1</CashierFlag><CashierNum>1</CashierNum><AmountDiscountType>0</AmountDiscountType><ClubDealFlag>0</ClubDealFlag><CustID>0</CustID><AmountDiscountPercent>0</AmountDiscountPercent><RefundMode>0</RefundMode><Components><Component ID=""><PluCode>1</PluCode><Title>כללי</Title><CompAmount>8</CompAmount><CompCashDiscount>0</CompCashDiscount><CompDiscount>0</CompDiscount><CodeFlag>1</CodeFlag><StockAmount>1</StockAmount><DiscountType>0</DiscountType><SecondDiscFlag>0</SecondDiscFlag><SecondFreeFlag>0</SecondFreeFlag><OtherDiscountFlag>0</OtherDiscountFlag><ClubDiscount>0</ClubDiscount><AmountPercentDiscount>0</AmountPercentDiscount><DepartmentFlag>0</DepartmentFlag><DepartmentNum>0</DepartmentNum><WeigthFlag>0</WeigthFlag><WeightQty>1</WeightQty></Component></Components><Payments><Payment ID=""><PaymID>1</PaymID><CashSum>8</CashSum><ChequeSum>0.00</ChequeSum><FullData>0</FullData><ChequeNumber></ChequeNumber><PayDate></PayDate><BankNo>0</BankNo><BankDeptNo>0</BankDeptNo><BankCntNo></BankCntNo><CouponSum>0.00</CouponSum><CouponNumber>0</CouponNumber><FrnCurrSum>0.00</FrnCurrSum><CurrencyID>0</CurrencyID><IsInShekels>0</IsInShekels><CreditCardSum>0.00</CreditCardSum><FirstPayment>0.00</FirstPayment><OtherPayment>0.00</OtherPayment><CardNum></CardNum><ExpDate>0</ExpDate><CreditTerms>0</CreditTerms><CompanyNum>0</CompanyNum><NumPayments>0</NumPayments><TranCode>0</TranCode><TranType>0</TranType><AuthorizCode>0</AuthorizCode><Currency>0</Currency><AuthorizNo>0</AuthorizNo><Deposited>0</Deposited><Track2></Track2><Track2Len>0</Track2Len><FileNum>0</FileNum><CTransCount>0</CTransCount><ComReason>0</ComReason><CochavAmount>0.00</CochavAmount><ClubCode>0</ClubCode><HakafaSum>0.00</HakafaSum><CustID>0</CustID><IsRefundVoucher>0</IsRefundVoucher><IsChangingVoucher>0</IsChangingVoucher></Payment></Payments></Transaction><Transaction ID="" Terminal="1241" ChnNum="4060023"><TranNum>14907</TranNum><JournalNum>406</JournalNum><TranAmount>10</TranAmount><TranDiscount>0</TranDiscount><TranCashDiscount>0</TranCashDiscount><tChange>0</tChange><TranDate>2013-06-03</TranDate><TranTime>16:51:44</TranTime><IsRefund>0</IsRefund><IsDebtPayment>1</IsDebtPayment><CashierFlag>1</CashierFlag><CashierNum>1</CashierNum><AmountDiscountType>0</AmountDiscountType><ClubDealFlag>0</ClubDealFlag><CustID>0</CustID><AmountDiscountPercent>0</AmountDiscountPercent><RefundMode>0</RefundMode><Components><Component ID=""><PluCode>1</PluCode><Title>כללי</Title><CompAmount>10</CompAmount><CompCashDiscount>0</CompCashDiscount><CompDiscount>0</CompDiscount><CodeFlag>1</CodeFlag><StockAmount>1</StockAmount><DiscountType>0</DiscountType><SecondDiscFlag>0</SecondDiscFlag><SecondFreeFlag>0</SecondFreeFlag><OtherDiscountFlag>0</OtherDiscountFlag><ClubDiscount>0</ClubDiscount><AmountPercentDiscount>0</AmountPercentDiscount><DepartmentFlag>0</DepartmentFlag><DepartmentNum>0</DepartmentNum><WeigthFlag>0</WeigthFlag><WeightQty>1</WeightQty></Component></Components><Payments><Payment ID=""><PaymID>1</PaymID><CashSum>10</CashSum><ChequeSum>0.00</ChequeSum><FullData>0</FullData><ChequeNumber></ChequeNumber><PayDate></PayDate><BankNo>0</BankNo><BankDeptNo>0</BankDeptNo><BankCntNo></BankCntNo><CouponSum>0.00</CouponSum><CouponNumber>0</CouponNumber><FrnCurrSum>0.00</FrnCurrSum><CurrencyID>0</CurrencyID><IsInShekels>0</IsInShekels><CreditCardSum>0.00</CreditCardSum><FirstPayment>0.00</FirstPayment><OtherPayment>0.00</OtherPayment><CardNum></CardNum><ExpDate>0</ExpDate><CreditTerms>0</CreditTerms><CompanyNum>0</CompanyNum><NumPayments>0</NumPayments><TranCode>0</TranCode><TranType>0</TranType><AuthorizCode>0</AuthorizCode><Currency>0</Currency><AuthorizNo>0</AuthorizNo><Deposited>0</Deposited><Track2></Track2><Track2Len>0</Track2Len><FileNum>0</FileNum><CTransCount>0</CTransCount><ComReason>0</ComReason><CochavAmount>0.00</CochavAmount><ClubCode>0</ClubCode><HakafaSum>0.00</HakafaSum><CustID>0</CustID><IsRefundVoucher>0</IsRefundVoucher><IsChangingVoucher>0</IsChangingVoucher></Payment></Payments></Transaction><Transaction ID="" Terminal="1241" ChnNum="4060024"><TranNum>14908</TranNum><JournalNum>406</JournalNum><TranAmount>10</TranAmount><TranDiscount>0</TranDiscount><TranCashDiscount>0</TranCashDiscount><tChange>0</tChange><TranDate>2013-06-03</TranDate><TranTime>17:19:23</TranTime><IsRefund>0</IsRefund><IsDebtPayment>1</IsDebtPayment><CashierFlag>1</CashierFlag><CashierNum>1</CashierNum><AmountDiscountType>0</AmountDiscountType><ClubDealFlag>0</ClubDealFlag><CustID>0</CustID><AmountDiscountPercent>0</AmountDiscountPercent><RefundMode>0</RefundMode><Components><Component ID=""><PluCode>1</PluCode><Title>כללי</Title><CompAmount>10</CompAmount><CompCashDiscount>0</CompCashDiscount><CompDiscount>0</CompDiscount><CodeFlag>1</CodeFlag><StockAmount>1</StockAmount><DiscountType>0</DiscountType><SecondDiscFlag>0</SecondDiscFlag><SecondFreeFlag>0</SecondFreeFlag><OtherDiscountFlag>0</OtherDiscountFlag><ClubDiscount>0</ClubDiscount><AmountPercentDiscount>0</AmountPercentDiscount><DepartmentFlag>0</DepartmentFlag><DepartmentNum>0</DepartmentNum><WeigthFlag>0</WeigthFlag><WeightQty>1</WeightQty></Component></Components><Payments><Payment ID=""><PaymID>1</PaymID><CashSum>10</CashSum><ChequeSum>0.00</ChequeSum><FullData>0</FullData><ChequeNumber></ChequeNumber><PayDate></PayDate><BankNo>0</BankNo><BankDeptNo>0</BankDeptNo><BankCntNo></BankCntNo><CouponSum>0.00</CouponSum><CouponNumber>0</CouponNumber><FrnCurrSum>0.00</FrnCurrSum><CurrencyID>0</CurrencyID><IsInShekels>0</IsInShekels><CreditCardSum>0.00</CreditCardSum><FirstPayment>0.00</FirstPayment><OtherPayment>0.00</OtherPayment><CardNum></CardNum><ExpDate>0</ExpDate><CreditTerms>0</CreditTerms><CompanyNum>0</CompanyNum><NumPayments>0</NumPayments><TranCode>0</TranCode><TranType>0</TranType><AuthorizCode>0</AuthorizCode><Currency>0</Currency><AuthorizNo>0</AuthorizNo><Deposited>0</Deposited><Track2></Track2><Track2Len>0</Track2Len><FileNum>0</FileNum><CTransCount>0</CTransCount><ComReason>0</ComReason><CochavAmount>0.00</CochavAmount><ClubCode>0</ClubCode><HakafaSum>0.00</HakafaSum><CustID>0</CustID><IsRefundVoucher>0</IsRefundVoucher><IsChangingVoucher>0</IsChangingVoucher></Payment></Payments></Transaction><Transaction ID="" Terminal="1241" ChnNum="4060025"><TranNum>14909</TranNum><JournalNum>406</JournalNum><TranAmount>24</TranAmount><TranDiscount>0</TranDiscount><TranCashDiscount>0</TranCashDiscount><tChange>0</tChange><TranDate>2013-06-03</TranDate><TranTime>17:23:13</TranTime><IsRefund>0</IsRefund><IsDebtPayment>1</IsDebtPayment><CashierFlag>1</CashierFlag><CashierNum>1</CashierNum><AmountDiscountType>0</AmountDiscountType><ClubDealFlag>0</ClubDealFlag><CustID>0</CustID><AmountDiscountPercent>0</AmountDiscountPercent><RefundMode>0</RefundMode><Components><Component ID=""><PluCode>107212</PluCode><Title>צינור למכונת כביסה 2 מ'</Title><CompAmount>24</CompAmount><CompCashDiscount>0</CompCashDiscount><CompDiscount>0</CompDiscount><CodeFlag>1</CodeFlag><StockAmount>1</StockAmount><DiscountType>0</DiscountType><SecondDiscFlag>0</SecondDiscFlag><SecondFreeFlag>0</SecondFreeFlag><OtherDiscountFlag>0</OtherDiscountFlag><ClubDiscount>0</ClubDiscount><AmountPercentDiscount>0</AmountPercentDiscount><DepartmentFlag>0</DepartmentFlag><DepartmentNum>0</DepartmentNum><WeigthFlag>0</WeigthFlag><WeightQty>1</WeightQty></Component></Components><Payments><Payment ID=""><PaymID>5</PaymID><CashSum>0.00</CashSum><ChequeSum>0.00</ChequeSum><FullData>0</FullData><ChequeNumber></ChequeNumber><PayDate></PayDate><BankNo>0</BankNo><BankDeptNo>0</BankDeptNo><BankCntNo></BankCntNo><CouponSum>0.00</CouponSum><CouponNumber>0</CouponNumber><FrnCurrSum>0.00</FrnCurrSum><CurrencyID>0</CurrencyID><IsInShekels>0</IsInShekels><CreditCardSum>24</CreditCardSum><FirstPayment>24</FirstPayment><OtherPayment>24</OtherPayment><CardNum>5326101304658620</CardNum><ExpDate>2015-02-01 00:00:00</ExpDate><CreditTerms>1</CreditTerms><CompanyNum>1</CompanyNum><NumPayments>1</NumPayments><TranCode>Regular</TranCode><TranType>1</TranType><AuthorizCode>Manual</AuthorizCode><Currency>1</Currency><AuthorizNo></AuthorizNo><Deposited>0</Deposited><Track2></Track2><Track2Len>0</Track2Len><FileNum>0</FileNum><CTransCount>0</CTransCount><ComReason>2</ComReason><CochavAmount>0</CochavAmount><ClubCode>0</ClubCode><HakafaSum>0.00</HakafaSum><CustID>0</CustID><IsRefundVoucher>0</IsRefundVoucher><IsChangingVoucher>0</IsChangingVoucher></Payment></Payments></Transaction><Transaction ID="" Terminal="1241" ChnNum="4060026"><TranNum>14910</TranNum><JournalNum>406</JournalNum><TranAmount>35</TranAmount><TranDiscount>0</TranDiscount><TranCashDiscount>0</TranCashDiscount><tChange>0</tChange><TranDate>2013-06-03</TranDate><TranTime>17:24:37</TranTime><IsRefund>0</IsRefund><IsDebtPayment>1</IsDebtPayment><CashierFlag>1</CashierFlag><CashierNum>1</CashierNum><AmountDiscountType>0</AmountDiscountType><ClubDealFlag>0</ClubDealFlag><CustID>0</CustID><AmountDiscountPercent>0</AmountDiscountPercent><RefundMode>0</RefundMode><Components><Component ID=""><PluCode>1</PluCode><Title>כללי</Title><CompAmount>35</CompAmount><CompCashDiscount>0</CompCashDiscount><CompDiscount>0</CompDiscount><CodeFlag>1</CodeFlag><StockAmount>1</StockAmount><DiscountType>0</DiscountType><SecondDiscFlag>0</SecondDiscFlag><SecondFreeFlag>0</SecondFreeFlag><OtherDiscountFlag>0</OtherDiscountFlag><ClubDiscount>0</ClubDiscount><AmountPercentDiscount>0</AmountPercentDiscount><DepartmentFlag>0</DepartmentFlag><DepartmentNum>0</DepartmentNum><WeigthFlag>0</WeigthFlag><WeightQty>1</WeightQty></Component></Components><Payments><Payment ID=""><PaymID>1</PaymID><CashSum>35</CashSum><ChequeSum>0.00</ChequeSum><FullData>0</FullData><ChequeNumber></ChequeNumber><PayDate></PayDate><BankNo>0</BankNo><BankDeptNo>0</BankDeptNo><BankCntNo></BankCntNo><CouponSum>0.00</CouponSum><CouponNumber>0</CouponNumber><FrnCurrSum>0.00</FrnCurrSum><CurrencyID>0</CurrencyID><IsInShekels>0</IsInShekels><CreditCardSum>0.00</CreditCardSum><FirstPayment>0.00</FirstPayment><OtherPayment>0.00</OtherPayment><CardNum></CardNum><ExpDate>0</ExpDate><CreditTerms>0</CreditTerms><CompanyNum>0</CompanyNum><NumPayments>0</NumPayments><TranCode>0</TranCode><TranType>0</TranType><AuthorizCode>0</AuthorizCode><Currency>0</Currency><AuthorizNo>0</AuthorizNo><Deposited>0</Deposited><Track2></Track2><Track2Len>0</Track2Len><FileNum>0</FileNum><CTransCount>0</CTransCount><ComReason>0</ComReason><CochavAmount>0.00</CochavAmount><ClubCode>0</ClubCode><HakafaSum>0.00</HakafaSum><CustID>0</CustID><IsRefundVoucher>0</IsRefundVoucher><IsChangingVoucher>0</IsChangingVoucher></Payment></Payments></Transaction><Transaction ID="" Terminal="1241" ChnNum="4060027"><TranNum>14911</TranNum><JournalNum>406</JournalNum><TranAmount>15</TranAmount><TranDiscount>0</TranDiscount><TranCashDiscount>0</TranCashDiscount><tChange>0</tChange><TranDate>2013-06-03</TranDate><TranTime>17:45:27</TranTime><IsRefund>0</IsRefund><IsDebtPayment>1</IsDebtPayment><CashierFlag>1</CashierFlag><CashierNum>1</CashierNum><AmountDiscountType>0</AmountDiscountType><ClubDealFlag>0</ClubDealFlag><CustID>0</CustID><AmountDiscountPercent>0</AmountDiscountPercent><RefundMode>0</RefundMode><Components><Component ID=""><PluCode>1</PluCode><Title>כללי</Title><CompAmount>15</CompAmount><CompCashDiscount>0</CompCashDiscount><CompDiscount>0</CompDiscount><CodeFlag>1</CodeFlag><StockAmount>1</StockAmount><DiscountType>0</DiscountType><SecondDiscFlag>0</SecondDiscFlag><SecondFreeFlag>0</SecondFreeFlag><OtherDiscountFlag>0</OtherDiscountFlag><ClubDiscount>0</ClubDiscount><AmountPercentDiscount>0</AmountPercentDiscount><DepartmentFlag>0</DepartmentFlag><DepartmentNum>0</DepartmentNum><WeigthFlag>0</WeigthFlag><WeightQty>1</WeightQty></Component></Components><Payments><Payment ID=""><PaymID>1</PaymID><CashSum>15</CashSum><ChequeSum>0.00</ChequeSum><FullData>0</FullData><ChequeNumber></ChequeNumber><PayDate></PayDate><BankNo>0</BankNo><BankDeptNo>0</BankDeptNo><BankCntNo></BankCntNo><CouponSum>0.00</CouponSum><CouponNumber>0</CouponNumber><FrnCurrSum>0.00</FrnCurrSum><CurrencyID>0</CurrencyID><IsInShekels>0</IsInShekels><CreditCardSum>0.00</CreditCardSum><FirstPayment>0.00</FirstPayment><OtherPayment>0.00</OtherPayment><CardNum></CardNum><ExpDate>0</ExpDate><CreditTerms>0</CreditTerms><CompanyNum>0</CompanyNum><NumPayments>0</NumPayments><TranCode>0</TranCode><TranType>0</TranType><AuthorizCode>0</AuthorizCode><Currency>0</Currency><AuthorizNo>0</AuthorizNo><Deposited>0</Deposited><Track2></Track2><Track2Len>0</Track2Len><FileNum>0</FileNum><CTransCount>0</CTransCount><ComReason>0</ComReason><CochavAmount>0.00</CochavAmount><ClubCode>0</ClubCode><HakafaSum>0.00</HakafaSum><CustID>0</CustID><IsRefundVoucher>0</IsRefundVoucher><IsChangingVoucher>0</IsChangingVoucher></Payment></Payments></Transaction><Transaction ID="" Terminal="1241" ChnNum="4060028"><TranNum>14912</TranNum><JournalNum>406</JournalNum><TranAmount>6.9</TranAmount><TranDiscount>0</TranDiscount><TranCashDiscount>0</TranCashDiscount><tChange>0</tChange><TranDate>2013-06-03</TranDate><TranTime>19:02:05</TranTime><IsRefund>0</IsRefund><IsDebtPayment>1</IsDebtPayment><CashierFlag>1</CashierFlag><CashierNum>1</CashierNum><AmountDiscountType>0</AmountDiscountType><ClubDealFlag>0</ClubDealFlag><CustID>0</CustID><AmountDiscountPercent>0</AmountDiscountPercent><RefundMode>0</RefundMode><Components><Component ID=""><PluCode>1071</PluCode><Title>מלט שחור 2 ק"ג</Title><CompAmount>6.9</CompAmount><CompCashDiscount>0</CompCashDiscount><CompDiscount>0</CompDiscount><CodeFlag>1</CodeFlag><StockAmount>1</StockAmount><DiscountType>0</DiscountType><SecondDiscFlag>0</SecondDiscFlag><SecondFreeFlag>0</SecondFreeFlag><OtherDiscountFlag>0</OtherDiscountFlag><ClubDiscount>0</ClubDiscount><AmountPercentDiscount>0</AmountPercentDiscount><DepartmentFlag>0</DepartmentFlag><DepartmentNum>0</DepartmentNum><WeigthFlag>0</WeigthFlag><WeightQty>1</WeightQty></Component></Components><Payments><Payment ID=""><PaymID>1</PaymID><CashSum>6.9</CashSum><ChequeSum>0.00</ChequeSum><FullData>0</FullData><ChequeNumber></ChequeNumber><PayDate></PayDate><BankNo>0</BankNo><BankDeptNo>0</BankDeptNo><BankCntNo></BankCntNo><CouponSum>0.00</CouponSum><CouponNumber>0</CouponNumber><FrnCurrSum>0.00</FrnCurrSum><CurrencyID>0</CurrencyID><IsInShekels>0</IsInShekels><CreditCardSum>0.00</CreditCardSum><FirstPayment>0.00</FirstPayment><OtherPayment>0.00</OtherPayment><CardNum></CardNum><ExpDate>0</ExpDate><CreditTerms>0</CreditTerms><CompanyNum>0</CompanyNum><NumPayments>0</NumPayments><TranCode>0</TranCode><TranType>0</TranType><AuthorizCode>0</AuthorizCode><Currency>0</Currency><AuthorizNo>0</AuthorizNo><Deposited>0</Deposited><Track2></Track2><Track2Len>0</Track2Len><FileNum>0</FileNum><CTransCount>0</CTransCount><ComReason>0</ComReason><CochavAmount>0.00</CochavAmount><ClubCode>0</ClubCode><HakafaSum>0.00</HakafaSum><CustID>0</CustID><IsRefundVoucher>0</IsRefundVoucher><IsChangingVoucher>0</IsChangingVoucher></Payment></Payments></Transaction><Transaction ID="" Terminal="1241" ChnNum="4060029"><TranNum>14913</TranNum><JournalNum>406</JournalNum><TranAmount>42</TranAmount><TranDiscount>0</TranDiscount><TranCashDiscount>0</TranCashDiscount><tChange>0</tChange><TranDate>2013-06-03</TranDate><TranTime>19:21:27</TranTime><IsRefund>0</IsRefund><IsDebtPayment>1</IsDebtPayment><CashierFlag>1</CashierFlag><CashierNum>1</CashierNum><AmountDiscountType>0</AmountDiscountType><ClubDealFlag>0</ClubDealFlag><CustID>0</CustID><AmountDiscountPercent>0</AmountDiscountPercent><RefundMode>0</RefundMode><Components><Component ID=""><PluCode>68423</PluCode><Title>גליל ניילון פאר 2X50</Title><CompAmount>42</CompAmount><CompCashDiscount>0</CompCashDiscount><CompDiscount>0</CompDiscount><CodeFlag>1</CodeFlag><StockAmount>1</StockAmount><DiscountType>0</DiscountType><SecondDiscFlag>0</SecondDiscFlag><SecondFreeFlag>0</SecondFreeFlag><OtherDiscountFlag>0</OtherDiscountFlag><ClubDiscount>0</ClubDiscount><AmountPercentDiscount>0</AmountPercentDiscount><DepartmentFlag>0</DepartmentFlag><DepartmentNum>0</DepartmentNum><WeigthFlag>0</WeigthFlag><WeightQty>1</WeightQty></Component></Components><Payments><Payment ID=""><PaymID>5</PaymID><CashSum>0.00</CashSum><ChequeSum>0.00</ChequeSum><FullData>0</FullData><ChequeNumber></ChequeNumber><PayDate></PayDate><BankNo>0</BankNo><BankDeptNo>0</BankDeptNo><BankCntNo></BankCntNo><CouponSum>0.00</CouponSum><CouponNumber>0</CouponNumber><FrnCurrSum>0.00</FrnCurrSum><CurrencyID>0</CurrencyID><IsInShekels>0</IsInShekels><CreditCardSum>42</CreditCardSum><FirstPayment>42</FirstPayment><OtherPayment>42</OtherPayment><CardNum>4580030213031252</CardNum><ExpDate>2015-11-01 00:00:00</ExpDate><CreditTerms>1</CreditTerms><CompanyNum>2</CompanyNum><NumPayments>1</NumPayments><TranCode>Regular</TranCode><TranType>1</TranType><AuthorizCode>Manual</AuthorizCode><Currency>1</Currency><AuthorizNo></AuthorizNo><Deposited>0</Deposited><Track2></Track2><Track2Len>0</Track2Len><FileNum>0</FileNum><CTransCount>0</CTransCount><ComReason>2</ComReason><CochavAmount>0</CochavAmount><ClubCode>0</ClubCode><HakafaSum>0.00</HakafaSum><CustID>0</CustID><IsRefundVoucher>0</IsRefundVoucher><IsChangingVoucher>0</IsChangingVoucher></Payment></Payments></Transaction></Transactions>